ExasolMonitoringPlugins/__init__.py
ExasolMonitoringPlugins/check_backup.py
ExasolMonitoringPlugins/check_db_diskspace.py
ExasolMonitoringPlugins/check_db_performance.py
ExasolMonitoringPlugins/check_logservice.py
ExasolMonitoringPlugins/check_nodes.py
ExasolMonitoringPlugins/check_services.py
ExasolMonitoringPlugins-2019.7.dist-info/LICENSE
ExasolMonitoringPlugins-2019.7.dist-info/METADATA
ExasolMonitoringPlugins-2019.7.dist-info/WHEEL
ExasolMonitoringPlugins-2019.7.dist-info/top_level.txt
ExasolMonitoringPlugins-2019.7.dist-info/RECORD
